xmemory/__init__.py
xmemory/attribute.py
xmemory-0.1a1.dist-info/LICENSE
xmemory-0.1a1.dist-info/METADATA
xmemory-0.1a1.dist-info/WHEEL
xmemory-0.1a1.dist-info/top_level.txt
xmemory-0.1a1.dist-info/zip-safe
xmemory-0.1a1.dist-info/RECORD
