Metadata-Version: 2.1
Name: xmemory
Version: 0.1a1
Summary: Memory usage analysis
Home-page: https://github.com/bondbox/xmemory/
Author: Mingzhe Zou
Author-email: zoumingzhe@outlook.com
License: GPLv2
Project-URL: Source Code, https://github.com/bondbox/xmemory/
Project-URL: Bug Tracker, https://github.com/bondbox/xmemory/issues
Project-URL: Documentation, https://github.com/bondbox/xmemory/
Keywords: command-line,argparse,argcomplete
Platform: any
Classifier: Programming Language :: Python
Classifier: Programming Language :: Python :: 3
Requires-Python: >=3.8
License-File: LICENSE
